pashword/__init__.py
pashword/__main__.py
pashword/_version.py
pashword/default.conf
pashword/core/__init__.py
pashword/core/book.py
pashword/core/colors.py
pashword/core/pash.py
pashword/core/sets.py
pashword/main/__init__.py
pashword/main/read.py
pashword/main/sort.py
pashword-1.2.1.dist-info/LICENSE.txt
pashword-1.2.1.dist-info/METADATA
pashword-1.2.1.dist-info/WHEEL
pashword-1.2.1.dist-info/entry_points.txt
pashword-1.2.1.dist-info/top_level.txt
pashword-1.2.1.dist-info/RECORD
