Metadata-Version: 2.1
Name: pashword
Version: 1.2.1
Summary: Package to secure your passwords.
Author-email: Dunstan Becht <dunstan.becht@orange.fr>
Project-URL: Homepage, https://gitlab.com/dustils/pashword
Project-URL: Bug Tracker, https://gitlab.com/dustils/pashword/issues
Project-URL: Documentation, https://dustils.gitlab.io/pashword
Classifier: Programming Language :: Python :: 3
Classifier: License :: OSI Approved :: GNU General Public License v3 (GPLv3)
Classifier: Operating System :: OS Independent
Classifier: Topic :: Utilities
Classifier: Topic :: Security :: Cryptography
Classifier: Intended Audience :: End Users/Desktop
Requires-Python: >=3.9
License-File: LICENSE.txt
